chatbot_eval_common/__init__.py
chatbot_eval_common/events.py
chatbot_eval_common/py.typed
chatbot_eval_common-0.1.0.dist-info/METADATA
chatbot_eval_common-0.1.0.dist-info/WHEEL
chatbot_eval_common-0.1.0.dist-info/RECORD
